README.md
setup.py
distributions/NotebookCSS.py
distributions/Setting01.py
distributions/__init__.py
seongjaeryu.egg-info/PKG-INFO
seongjaeryu.egg-info/SOURCES.txt
seongjaeryu.egg-info/dependency_links.txt
seongjaeryu.egg-info/not-zip-safe
seongjaeryu.egg-info/top_level.txt