Metadata-Version: 1.0
Name: seongjaeryu
Version: 0.1
Summary: Seongjae Ryu's personal Python setting
Home-page: https://seongjaeryu.com
Author: Seongjae Ryu
Author-email: seongjaeryu@gmail.com
License: UNKNOWN
Keywords: seongjae ryu
Platform: UNKNOWN
